[
  {
    "text": "I have learnt to observe my thoughts better",
    "intent": "interpretation",
    "intent_prediction": {
      "name": "situation",
      "confidence": 0.3615950644016266
    }
  },
  {
    "text": "I can now point in the direction I need to work upon myself",
    "intent": "advantages_of_acting",
    "intent_prediction": {
      "name": "thought",
      "confidence": 0.8270359039306641
    }
  },
  {
    "text": "Because sometimes my thoughts aren’t true, and if I can figure out what I’m thinking, I can change it around and feel better.",
    "intent": "explain",
    "intent_prediction": {
      "name": "doubt",
      "confidence": 0.5348746180534363
    }
  },
  {
    "text": "I just pretended that I did not see him",
    "intent": "behavior",
    "intent_prediction": {
      "name": "thought",
      "confidence": 0.4083360433578491
    }
  },
  {
    "text": "goodevening",
    "intent": "greet",
    "intent_prediction": {
      "name": "situation_area",
      "confidence": 0.8044138550758362
    }
  },
  {
    "text": "I didn’t do well last time",
    "intent": "evidence_for",
    "intent_prediction": {
      "name": "feeling",
      "confidence": 0.9594178795814514
    }
  },
  {
    "text": "Many people forgot my birthday",
    "intent": "evidence_for",
    "intent_prediction": {
      "name": "evidence_against",
      "confidence": 0.6366882920265198
    }
  },
  {
    "text": "The professor has praised me before for my knowledge",
    "intent": "evidence_against",
    "intent_prediction": {
      "name": "evidence_for",
      "confidence": 0.934390664100647
    }
  },
  {
    "text": "The average marks of the class itself was very low",
    "intent": "evidence_against",
    "intent_prediction": {
      "name": "situation",
      "confidence": 0.5656276941299438
    }
  },
  {
    "text": "Applying to colleges has a lot of luck factor in it",
    "intent": "evidence_against",
    "intent_prediction": {
      "name": "telling_friend",
      "confidence": 0.32369670271873474
    }
  },
  {
    "text": "I was just having a bad day",
    "intent": "evidence_against",
    "intent_prediction": {
      "name": "feeling",
      "confidence": 0.88991779088974
    }
  },
  {
    "text": "Inside my head",
    "intent": "felt_where",
    "intent_prediction": {
      "name": "feeling",
      "confidence": 0.48680657148361206
    }
  },
  {
    "text": "I feel anxious about the stock market",
    "intent": "thought+situation",
    "intent_prediction": {
      "name": "doubt",
      "confidence": 0.5336984395980835
    }
  },
  {
    "text": "I feel very clumsy about myself",
    "intent": "thought+situation",
    "intent_prediction": {
      "name": "feeling",
      "confidence": 0.97580486536026
    }
  },
  {
    "text": "I have the ability to move on from this failure",
    "intent": "positive_belief",
    "intent_prediction": {
      "name": "negative_belief",
      "confidence": 0.5177489519119263
    }
  },
  {
    "text": "This just seems like the perfect path",
    "intent": "positive_belief",
    "intent_prediction": {
      "name": "thought",
      "confidence": 0.44503432512283325
    }
  },
  {
    "text": "I strongly disagree",
    "intent": "disagree",
    "intent_prediction": {
      "name": "agree",
      "confidence": 0.46399492025375366
    }
  },
  {
    "text": "What do I do now ?",
    "intent": "doubt",
    "intent_prediction": {
      "name": "thought",
      "confidence": 0.9992795586585999
    }
  },
  {
    "text": "I am not sure if I am capable of doing this or not",
    "intent": "doubt",
    "intent_prediction": {
      "name": "positive_belief",
      "confidence": 0.4238933324813843
    }
  },
  {
    "text": "negative belief",
    "intent": "doubt",
    "intent_prediction": {
      "name": "situation_area",
      "confidence": 0.35683226585388184
    }
  },
  {
    "text": "No one thinks of me as a friend",
    "intent": "negative_belief",
    "intent_prediction": {
      "name": "thought",
      "confidence": 0.9758157730102539
    }
  },
  {
    "text": "Nobody found time to attend the party I was throwing",
    "intent": "situation",
    "intent_prediction": {
      "name": "evidence_against",
      "confidence": 0.18543073534965515
    }
  },
  {
    "text": "I had fever",
    "intent": "situation",
    "intent_prediction": {
      "name": "feeling",
      "confidence": 0.48233136534690857
    }
  },
  {
    "text": "kids don't study",
    "intent": "situation",
    "intent_prediction": {
      "name": "situation_area",
      "confidence": 0.44395148754119873
    }
  },
  {
    "text": "I do not play with Rubik's cube.",
    "intent": "situation",
    "intent_prediction": {
      "name": "feeling+situation",
      "confidence": 0.913337230682373
    }
  },
  {
    "text": "My colleagues judge me on the college I graduated from",
    "intent": "thought",
    "intent_prediction": {
      "name": "situation",
      "confidence": 0.9973011612892151
    }
  },
  {
    "text": "My heart started beating real fast and I thought, “What’s wrong with me?”",
    "intent": "thought",
    "intent_prediction": {
      "name": "felt_where",
      "confidence": 0.41027161478996277
    }
  },
  {
    "text": "That I’m not smart enough. I don’t have what it takes.",
    "intent": "thought",
    "intent_prediction": {
      "name": "negative_belief",
      "confidence": 0.24585753679275513
    }
  },
  {
    "text": "No, not at all! I was thinking that I don’t know whether I belong here.",
    "intent": "thought",
    "intent_prediction": {
      "name": "disagree",
      "confidence": 0.2897282838821411
    }
  },
  {
    "text": "If I say something, it won't come out right. People will judge.",
    "intent": "thought",
    "intent_prediction": {
      "name": "explain",
      "confidence": 0.22212645411491394
    }
  },
  {
    "text": "I'd feel better",
    "intent": "feeling",
    "intent_prediction": {
      "name": "agree",
      "confidence": 0.28703561425209045
    }
  },
  {
    "text": "I don't feel like doing anything",
    "intent": "feeling",
    "intent_prediction": {
      "name": "doubt",
      "confidence": 0.6061567664146423
    }
  },
  {
    "text": "Everything vexes me",
    "intent": "feeling",
    "intent_prediction": {
      "name": "doubt",
      "confidence": 0.5426286458969116
    }
  },
  {
    "text": "I have no patience today",
    "intent": "feeling",
    "intent_prediction": {
      "name": "negative_belief",
      "confidence": 0.3283329904079437
    }
  },
  {
    "text": "that would be a great relief if the paper were done, and I thought I'd done well.",
    "intent": "feeling",
    "intent_prediction": {
      "name": "agree",
      "confidence": 0.45266231894493103
    }
  }
]